zdpapi_modbus/__init__.py
zdpapi_modbus/device.py
zdpapi_modbus/device_async.py
zdpapi_modbus/funcs/__init__.py
zdpapi_modbus/funcs/writer.py
zdpapi_modbus/funcs.py
zdpapi_modbus/libs/__init__.py
zdpapi_modbus/libs/modbus_tk/__init__.py
zdpapi_modbus/libs/modbus_tk/defines.py
zdpapi_modbus/libs/modbus_tk/exceptions.py
zdpapi_modbus/libs/modbus_tk/hooks.py
zdpapi_modbus/libs/modbus_tk/modbus.py
zdpapi_modbus/libs/modbus_tk/modbus_rtu.py
zdpapi_modbus/libs/modbus_tk/modbus_rtu_over_tcp.py
zdpapi_modbus/libs/modbus_tk/modbus_tcp.py
zdpapi_modbus/libs/modbus_tk/simulator.py
zdpapi_modbus/libs/modbus_tk/simulator_rpc_client.py
zdpapi_modbus/libs/modbus_tk/utils.py
zdpapi_modbus/master.py
zdpapi_modbus/master_async.py
zdpapi_modbus/random.py
zdpapi_modbus/slave.py
zdpapi_modbus/zstruct.py
zdpapi_modbus-1.7.1.dist-info/LICENSE
zdpapi_modbus-1.7.1.dist-info/WHEEL
zdpapi_modbus-1.7.1.dist-info/METADATA
zdpapi_modbus-1.7.1.dist-info/RECORD
