Metadata-Version: 2.1
Name: zdpapi-modbus
Version: 1.7.1
Summary: python版modbus协议快速开发工具库
Home-page: https://github.com/zhangdapeng520/zdpapi_modbus
License: MIT
Keywords: zdpapi,modbus,zhangdapeng
Author: 张大鹏
Author-email: lxgzhw@163.com
Requires-Python: >=3.7,<4.0
Classifier: License :: OSI Approved :: MIT License
Classifier: Programming Language :: Python :: 3
Classifier: Programming Language :: Python :: 3.10
Classifier: Programming Language :: Python :: 3.7
Classifier: Programming Language :: Python :: 3.8
Classifier: Programming Language :: Python :: 3.9
Requires-Dist: aioredis[hiredis] (>=2.0.0,<3.0.0)
Requires-Dist: redis (>=4.0.2,<5.0.0)
Project-URL: Documentation, https://github.com/zhangdapeng520/zdpapi_modbus
Project-URL: Repository, https://github.com/zhangdapeng520/zdpapi_modbus
